aisaratuners/__init__.py
aisaratuners/aisara_general_tuner.py
aisaratuners/aisara_keras_tuner.py
aisaratuners-1.5.2.dist-info/LICENSE.txt
aisaratuners-1.5.2.dist-info/METADATA
aisaratuners-1.5.2.dist-info/WHEEL
aisaratuners-1.5.2.dist-info/top_level.txt
aisaratuners-1.5.2.dist-info/RECORD
