Metadata-Version: 2.1
Name: aisaratuners
Version: 1.5.2
Summary: leveraging aisara algorithm for effective hyperparameter tuning
Home-page: UNKNOWN
Author: AiSara Artificial Intelligence
Author-email: devs@aisara.ai
License: LICENSE.txt
Project-URL: Source Code, https://github.com/aisara-hub/aisaratuners
Project-URL: Documentation, https://github.com/aisara-hub/aisaratuners/blob/master/docs/user%20guide.md
Project-URL: Tutorials, https://github.com/aisara-hub/aisaratuners/blob/master/docs/Tutorials.md
Platform: UNKNOWN
Classifier: Development Status :: 5 - Production/Stable
Classifier: Operating System :: OS Independent
Classifier: Programming Language :: Python :: 3
Requires-Python: >=3.6
License-File: LICENSE.txt
Requires-Dist: requests
Requires-Dist: pandas
Requires-Dist: numpy
Requires-Dist: plotly (>=4.6.0)
Requires-Dist: tensorflow (>=1.15)
